Tsallis_module/basic/TsallisMath.py
Tsallis_module/basic/__init__.py
Tsallis_module/basic/qMath.py
Tsallis_module/machine/__init__.py
Tsallis_module/statistics/TsallisStatistics.py
Tsallis_module/statistics/__init__.py
Tsallis_module/statistics/qStatistics.py
Tsallis_package-0.2.1.dist-info/LICENSE.txt
Tsallis_package-0.2.1.dist-info/METADATA
Tsallis_package-0.2.1.dist-info/WHEEL
Tsallis_package-0.2.1.dist-info/top_level.txt
Tsallis_package-0.2.1.dist-info/RECORD
