Metadata-Version: 2.1
Name: Tsallis_package
Version: 0.2.1
Summary: A package for all mathematics and physics concerning Tsallis statistics
Author-email: "Hermes A. V. Urquijo" <hvurquijo@duck.com>
Project-URL: Homepage, https://github.com/havurquijo/Tsallis_package
Project-URL: Issues, https://github.com/havurquijo/Tsallis_package/Issues
Classifier: Programming Language :: Python :: 3
Classifier: License :: OSI Approved :: GNU General Public License v3 (GPLv3)
Classifier: Operating System :: Microsoft :: Windows
Classifier: Operating System :: POSIX :: Linux
Requires-Python: >=3.12
License-File: LICENSE.txt
